pyppl_lock.py
pyppl_lock-0.0.5.dist-info/entry_points.txt
pyppl_lock-0.0.5.dist-info/LICENSE
pyppl_lock-0.0.5.dist-info/WHEEL
pyppl_lock-0.0.5.dist-info/METADATA
pyppl_lock-0.0.5.dist-info/RECORD
