Metadata-Version: 2.1
Name: pyppl-lock
Version: 0.0.5
Summary: Preventing running processes from running again for PyPPL
License: MIT
Author: pwwang
Author-email: pwwang@pwwang.com
Requires-Python: >=3.6,<4.0
Classifier: License :: OSI Approved :: MIT License
Classifier: Programming Language :: Python :: 3
Classifier: Programming Language :: Python :: 3.6
Classifier: Programming Language :: Python :: 3.7
Classifier: Programming Language :: Python :: 3.8
Requires-Dist: filelock (>=3,<4)
Requires-Dist: pyppl
